[
  {
    "LICENCIA": "6AS5D1A65D1",
    "NOMBRE": "PLANTA",
    "FECHA": "2025-09-12"
  },
  {
    "LICENCIA": "P3GQA-55COK-JPGP3-67HHW-MLO6Y",
    "NOMBRE": "TESTING",
    "FECHA": "2025-12-12"
  },
  {
    "LICENCIA": "DIKDQ-OW456-Y5CBD-LDSJV-TA6ZN",
    "NOMBRE": "HOLA",
    "FECHA": "2025-10-21"
  },
  {
    "LICENCIA": "2EQCU-ECQ3P-MRX2M-XWQPI-QW7YO",
    "NOMBRE": "2EQCU-ECQ3P-MRX2M-XWQPI-QW7YO",
    "FECHA": "2062-01-01"
  },
  {
    "LICENCIA": "KQX4B-AQL7J-2WCSH-G4FGF-5GJV2",
    "NOMBRE": "Yefree",
    "FECHA": "2026-01-01"
  }
]